Workbook

Sheet Instrucciones
A1: Reparto Bouw: dos socios, dos dueños
A3: Cómo funciona (3 capas)
A4: 1. PROPIEDAD: los dos son dueños (50/50 por defecto, en Parametros). Lo que queda en el Fondo Bouw es de los dos según ese %.
A5: 2. TRABAJO: de cada proyecto neto se paga Origen (quien consiguió el cliente), Líder (quien coordina) y Ejecución (según horas).
A6: 3. UTILIDAD ANUAL: el Fondo Bouw menos gastos e impuestos se reparte como dividendos según la propiedad.
A8: Qué llenar
A9: Parametros: nombres de los socios, % de propiedad, % de reparto y datos tributarios (celdas amarillas, texto azul).
A10: Horas: una fila por cada bloque de trabajo (fecha, ID de proyecto, socio, horas, tarea).
A11: Proyectos: una fila por proyecto o por cada mes de un cliente recurrente (ingreso sin IVA, costos directos, quién consiguió, quién lidera).
A12: Gastos: gastos de la empresa pagados con el Fondo Bouw (contador, herramientas, publicidad, etc.).
A13: Resumen: no se llena. Muestra lo que gana cada socio por mes y en el año, como trabajador y como dueño.
A15: Colores
... A23: El pago por trabajo (Origen, Líder, Ejecución) se muestra antes de impuestos personales y retenciones.

Sheet Parametros
A1: Parámetros del reparto
A3: Socios y propiedad
A4: Socio | B4: Nombre | C4: % de propiedad | D4: Especialidad | F4: Listas
A5: Socio 1 | B5: [Tu nombre] | C5: 0.5 | D5: Procesos (Ing. Industrial) | F5: =B5 | G5: Procesos
A6: Socio 2 | B6: [Nombre del socio] | C6: 0.5 | D6: Informático / Ciberseguridad | F6: =B6 | G6: Seguridad
A7: Total | C7: =C5+C6 | D7: =IF(ROUND(C7,6)=1,"OK","Revisar: debe sumar 100%") | F7: =B16 | G7: Mixto
A9: Reparto de cada proyecto (sobre el ingreso neto)
A10: Concepto | B10: % del neto | C10: Para quién | D10: Nota
A11: Fondo Bouw | B11: 0.2 | C11: La empresa (de los dos, según propiedad) | D11: Marketing, herramientas, contador, reservas e impuestos
A12: Origen | B12: 0.1 | C12: Quien consiguió el cliente | D12: Si el cliente llegó por la marca (web, redes), va al Fondo Bouw
A13: Líder del proyecto | B13: 0.1 | C13: Quien coordina y responde al cliente | D13: Lidera quien sabe del tema
A14: Ejecución | B14: =1-B11-B12-B13 | C14: Los dos, según horas registradas | D14: Se calcula solo: lo que resta
A15: Total | B15: =SUM(B11:B14) | D15: =IF(AND(ROUND(B15,6)=1,B14>=0),"OK","Revisar porcentajes")
A16: Opción de origen sin socio | B16: Bouw (marca) | D16: Elegir esta opción en Proyectos cuando el cliente llegó por la marca
A18: Datos del año y tributarios (confirmar con el contador)
A19: Concepto | B19: Valor | D19: Fuente / nota
A20: Año del reparto | B20: 2026 | D20: Año que se está registrando
A21: ¿Hay trabajadores en relación de dependencia? (Sí/No) | B21: No | D21: Si es Sí, se calcula el 15% de participación de trabajadores antes del impuesto a la renta
A22: Participación de trabajadores | B22: 0.15 | D22: Código del Trabajo; orden de reparto en SAS según EasyTax (easytaxec.com/blog/reparto-de-utilidades-en-una-sas)
A23: Tarifa de impuesto a la renta de sociedades | B23: 0.25 | D23: Supuesto: tarifa general. Confirmar si aplica tarifa reducida
A24: Reserva (si aplica) | B24: 0 | D24: Supuesto 0%. Confirmar con el contador si la SAS debe apartar reserva
A25: Porcentaje de la utilidad neta que se reinvierte | B25: 0 | D25: Decisión de los socios; el resto se reparte como dividendos
A26: Retención sobre dividendos (residentes) | B26: 0.12 | D26: Ley Orgánica de Transparencia Social (2025) y reglamento; SRI boletín 043
A27: Salario básico unificado del año (USD) | B27: 482 | D27: Supuesto: confirmar el valor oficial del año
A28: Salarios básicos exentos por socio | B28: 3 | D28: Franja exenta de 3 SBU por sociedad y persona natural residente (Contapp, dividendos 2026)
A29: Monto exento por socio (USD) | B29: =B27*B28 | D29: Se calcula solo

Sheet Resumen
A1: Resumen: cuánto gana cada socio como trabajador y como dueño
A2: ="Socio 1: "&Parametros!B5&" · Socio 2: "&Parametros!B6&" · Año "&Parametros!B20
A4: Mes | B4: Ingreso neto (USD) | C4: Trabajo socio 1 (USD) | D4: Trabajo socio 2 (USD) | E4: Aporte al Fondo Bouw (USD) | F4: Gastos de la empresa (USD) | G4: Fondo neto del mes (USD) | H4: Parte de dueño socio 1 (USD) | I4: Parte de dueño socio 2 (USD)
A5: Enero | B5: =SUMIFS(Proyectos!$J$5:$J$204,Proyectos!$D$5:$D$204,">="&DATE(Parametros!$B$20,1,1),Proyectos!$D$5:$D$204,"<"&DATE(Parametros!$B$20,1+1,1)) | C5: =SUMIFS(Proyectos!$U$5:$U$204,Proyectos!$D$5:$D$204,">="&DATE(Parametros!$B$20,1,1),Proyectos!$D$5:$D$204,"<"&DATE(Parametros!$B$20,1+1,1)) | D5: =SUMIFS(Proyectos!$V$5:$V$204,Proyectos!$D$5:$D$204,">="&DATE(Parametros!$B$20,1,1),Proyectos!$D$5:$D$204,"<"&DATE(Parametros!$B$20,1+1,1)) | E5: =SUMIFS(Proyectos!$N$5:$N$204,Proyectos!$D$5:$D$204,">="&DATE(Parametros!$B$20,1,1),Proyectos!$D$5:$D$204,"<"&DATE(Parametros!$B$20,1+1,1)) | F5: =SUMIFS(Gastos!$D$5:$D$204,Gastos!$A$5:$A$204,">="&DATE(Parametros!$B$20,1,1),Gastos!$A$5:$A$204,"<"&DATE(Parametros!$B$20,1+1,1)) | G5: =E5-F5 | H5: =G5*Parametros!$C$5 | I5: =G5*Parametros!$C$6
A6: Febrero | B6: =SUMIFS(Proyectos!$J$5:$J$204,Proyectos!$D$5:$D$204,">="&DATE(Parametros!$B$20,2,1),Proyectos!$D$5:$D$204,"<"&DATE(Parametros!$B$20,2+1,1)) | C6: =SUMIFS(Proyectos!$U$5:$U$204,Proyectos!$D$5:$D$204,">="&DATE(Parametros!$B$20,2,1),Proyectos!$D$5:$D$204,"<"&DATE(Parametros!$B$20,2+1,1)) | D6: =SUMIFS(Proyectos!$V$5:$V$204,Proyectos!$D$5:$D$204,">="&DATE(Parametros!$B$20,2,1),Proyectos!$D$5:$D$204,"<"&DATE(Parametros!$B$20,2+1,1)) | E6: =SUMIFS(Proyectos!$N$5:$N$204,Proyectos!$D$5:$D$204,">="&DATE(Parametros!$B$20,2,1),Proyectos!$D$5:$D$204,"<"&DATE(Parametros!$B$20,2+1,1)) | F6: =SUMIFS(Gastos!$D$5:$D$204,Gastos!$A$5:$A$204,">="&DATE(Parametros!$B$20,2,1),Gastos!$A$5:$A$204,"<"&DATE(Parametros!$B$20,2+1,1)) | G6: =E6-F6 | H6: =G6*Parametros!$C$5 | I6: =G6*Parametros!$C$6
A7: Marzo | B7: =SUMIFS(Proyectos!$J$5:$J$204,Proyectos!$D$5:$D$204,">="&DATE(Parametros!$B$20,3,1),Proyectos!$D$5:$D$204,"<"&DATE(Parametros!$B$20,3+1,1)) | C7: =SUMIFS(Proyectos!$U$5:$U$204,Proyectos!$D$5:$D$204,">="&DATE(Parametros!$B$20,3,1),Proyectos!$D$5:$D$204,"<"&DATE(Parametros!$B$20,3+1,1)) | D7: =SUMIFS(Proyectos!$V$5:$V$204,Proyectos!$D$5:$D$204,">="&DATE(Parametros!$B$20,3,1),Proyectos!$D$5:$D$204,"<"&DATE(Parametros!$B$20,3+1,1)) | E7: =SUMIFS(Proyectos!$N$5:$N$204,Proyectos!$D$5:$D$204,">="&DATE(Parametros!$B$20,3,1),Proyectos!$D$5:$D$204,"<"&DATE(Parametros!$B$20,3+1,1)) | F7: =SUMIFS(Gastos!$D$5:$D$204,Gastos!$A$5:$A$204,">="&DATE(Parametros!$B$20,3,1),Gastos!$A$5:$A$204,"<"&DATE(Parametros!$B$20,3+1,1)) | G7: =E7-F7 | H7: =G7*Parametros!$C$5 | I7: =G7*Parametros!$C$6
A8: Abril | B8: =SUMIFS(Proyectos!$J$5:$J$204,Proyectos!$D$5:$D$204,">="&DATE(Parametros!$B$20,4,1),Proyectos!$D$5:$D$204,"<"&DATE(Parametros!$B$20,4+1,1)) | C8: =SUMIFS(Proyectos!$U$5:$U$204,Proyectos!$D$5:$D$204,">="&DATE(Parametros!$B$20,4,1),Proyectos!$D$5:$D$204,"<"&DATE(Parametros!$B$20,4+1,1)) | D8: =SUMIFS(Proyectos!$V$5:$V$204,Proyectos!$D$5:$D$204,">="&DATE(Parametros!$B$20,4,1),Proyectos!$D$5:$D$204,"<"&DATE(Parametros!$B$20,4+1,1)) | E8: =SUMIFS(Proyectos!$N$5:$N$204,Proyectos!$D$5:$D$204,">="&DATE(Parametros!$B$20,4,1),Proyectos!$D$5:$D$204,"<"&DATE(Parametros!$B$20,4+1,1)) | F8: =SUMIFS(Gastos!$D$5:$D$204,Gastos!$A$5:$A$204,">="&DATE(Parametros!$B$20,4,1),Gastos!$A$5:$A$204,"<"&DATE(Parametros!$B$20,4+1,1)) | G8: =E8-F8 | H8: =G8*Parametros!$C$5 | I8: =G8*Parametros!$C$6
A9: Mayo | B9: =SUMIFS(Proyectos!$J$5:$J$204,Proyectos!$D$5:$D$204,">="&DATE(Parametros!$B$20,5,1),Proyectos!$D$5:$D$204,"<"&DATE(Parametros!$B$20,5+1,1)) | C9: =SUMIFS(Proyectos!$U$5:$U$204,Proyectos!$D$5:$D$204,">="&DATE(Parametros!$B$20,5,1),Proyectos!$D$5:$D$204,"<"&DATE(Parametros!$B$20,5+1,1)) | D9: =SUMIFS(Proyectos!$V$5:$V$204,Proyectos!$D$5:$D$204,">="&DATE(Parametros!$B$20,5,1),Proyectos!$D$5:$D$204,"<"&DATE(Parametros!$B$20,5+1,1)) | E9: =SUMIFS(Proyectos!$N$5:$N$204,Proyectos!$D$5:$D$204,">="&DATE(Parametros!$B$20,5,1),Proyectos!$D$5:$D$204,"<"&DATE(Parametros!$B$20,5+1,1)) | F9: =SUMIFS(Gastos!$D$5:$D$204,Gastos!$A$5:$A$204,">="&DATE(Parametros!$B$20,5,1),Gastos!$A$5:$A$204,"<"&DATE(Parametros!$B$20,5+1,1)) | G9: =E9-F9 | H9: =G9*Parametros!$C$5 | I9: =G9*Parametros!$C$6
A10: Junio | B10: =SUMIFS(Proyectos!$J$5:$J$204,Proyectos!$D$5:$D$204,">="&DATE(Parametros!$B$20,6,1),Proyectos!$D$5:$D$204,"<"&DATE(Parametros!$B$20,6+1,1)) | C10: =SUMIFS(Proyectos!$U$5:$U$204,Proyectos!$D$5:$D$204,">="&DATE(Parametros!$B$20,6,1),Proyectos!$D$5:$D$204,"<"&DATE(Parametros!$B$20,6+1,1)) | D10: =SUMIFS(Proyectos!$V$5:$V$204,Proyectos!$D$5:$D$204,">="&DATE(Parametros!$B$20,6,1),Proyectos!$D$5:$D$204,"<"&DATE(Parametros!$B$20,6+1,1)) | E10: =SUMIFS(Proyectos!$N$5:$N$204,Proyectos!$D$5:$D$204,">="&DATE(Parametros!$B$20,6,1),Proyectos!$D$5:$D$204,"<"&DATE(Parametros!$B$20,6+1,1)) | F10: =SUMIFS(Gastos!$D$5:$D$204,Gastos!$A$5:$A$204,">="&DATE(Parametros!$B$20,6,1),Gastos!$A$5:$A$204,"<"&DATE(Parametros!$B$20,6+1,1)) | G10: =E10-F10 | H10: =G10*Parametros!$C$5 | I10: =G10*Parametros!$C$6
A11: Julio | B11: =SUMIFS(Proyectos!$J$5:$J$204,Proyectos!$D$5:$D$204,">="&DATE(Parametros!$B$20,7,1),Proyectos!$D$5:$D$204,"<"&DATE(Parametros!$B$20,7+1,1)) | C11: =SUMIFS(Proyectos!$U$5:$U$204,Proyectos!$D$5:$D$204,">="&DATE(Parametros!$B$20,7,1),Proyectos!$D$5:$D$204,"<"&DATE(Parametros!$B$20,7+1,1)) | D11: =SUMIFS(Proyectos!$V$5:$V$204,Proyectos!$D$5:$D$204,">="&DATE(Parametros!$B$20,7,1),Proyectos!$D$5:$D$204,"<"&DATE(Parametros!$B$20,7+1,1)) | E11: =SUMIFS(Proyectos!$N$5:$N$204,Proyectos!$D$5:$D$204,">="&DATE(Parametros!$B$20,7,1),Proyectos!$D$5:$D$204,"<"&DATE(Parametros!$B$20,7+1,1)) | F11: =SUMIFS(Gastos!$D$5:$D$204,Gastos!$A$5:$A$204,">="&DATE(Parametros!$B$20,7,1),Gastos!$A$5:$A$204,"<"&DATE(Parametros!$B$20,7+1,1)) | G11: =E11-F11 | H11: =G11*Parametros!$C$5 | I11: =G11*Parametros!$C$6
A12: Agosto | B12: =SUMIFS(Proyectos!$J$5:$J$204,Proyectos!$D$5:$D$204,">="&DATE(Parametros!$B$20,8,1),Proyectos!$D$5:$D$204,"<"&DATE(Parametros!$B$20,8+1,1)) | C12: =SUMIFS(Proyectos!$U$5:$U$204,Proyectos!$D$5:$D$204,">="&DATE(Parametros!$B$20,8,1),Proyectos!$D$5:$D$204,"<"&DATE(Parametros!$B$20,8+1,1)) | D12: =SUMIFS(Proyectos!$V$5:$V$204,Proyectos!$D$5:$D$204,">="&DATE(Parametros!$B$20,8,1),Proyectos!$D$5:$D$204,"<"&DATE(Parametros!$B$20,8+1,1)) | E12: =SUMIFS(Proyectos!$N$5:$N$204,Proyectos!$D$5:$D$204,">="&DATE(Parametros!$B$20,8,1),Proyectos!$D$5:$D$204,"<"&DATE(Parametros!$B$20,8+1,1)) | F12: =SUMIFS(Gastos!$D$5:$D$204,Gastos!$A$5:$A$204,">="&DATE(Parametros!$B$20,8,1),Gastos!$A$5:$A$204,"<"&DATE(Parametros!$B$20,8+1,1)) | G12: =E12-F12 | H12: =G12*Parametros!$C$5 | I12: =G12*Parametros!$C$6
A13: Septiembre | B13: =SUMIFS(Proyectos!$J$5:$J$204,Proyectos!$D$5:$D$204,">="&DATE(Parametros!$B$20,9,1),Proyectos!$D$5:$D$204,"<"&DATE(Parametros!$B$20,9+1,1)) | C13: =SUMIFS(Proyectos!$U$5:$U$204,Proyectos!$D$5:$D$204,">="&DATE(Parametros!$B$20,9,1),Proyectos!$D$5:$D$204,"<"&DATE(Parametros!$B$20,9+1,1)) | D13: =SUMIFS(Proyectos!$V$5:$V$204,Proyectos!$D$5:$D$204,">="&DATE(Parametros!$B$20,9,1),Proyectos!$D$5:$D$204,"<"&DATE(Parametros!$B$20,9+1,1)) | E13: =SUMIFS(Proyectos!$N$5:$N$204,Proyectos!$D$5:$D$204,">="&DATE(Parametros!$B$20,9,1),Proyectos!$D$5:$D$204,"<"&DATE(Parametros!$B$20,9+1,1)) | F13: =SUMIFS(Gastos!$D$5:$D$204,Gastos!$A$5:$A$204,">="&DATE(Parametros!$B$20,9,1),Gastos!$A$5:$A$204,"<"&DATE(Parametros!$B$20,9+1,1)) | G13: =E13-F13 | H13: =G13*Parametros!$C$5 | I13: =G13*Parametros!$C$6
A14: Octubre | B14: =SUMIFS(Proyectos!$J$5:$J$204,Proyectos!$D$5:$D$204,">="&DATE(Parametros!$B$20,10,1),Proyectos!$D$5:$D$204,"<"&DATE(Parametros!$B$20,10+1,1)) | C14: =SUMIFS(Proyectos!$U$5:$U$204,Proyectos!$D$5:$D$204,">="&DATE(Parametros!$B$20,10,1),Proyectos!$D$5:$D$204,"<"&DATE(Parametros!$B$20,10+1,1)) | D14: =SUMIFS(Proyectos!$V$5:$V$204,Proyectos!$D$5:$D$204,">="&DATE(Parametros!$B$20,10,1),Proyectos!$D$5:$D$204,"<"&DATE(Parametros!$B$20,10+1,1)) | E14: =SUMIFS(Proyectos!$N$5:$N$204,Proyectos!$D$5:$D$204,">="&DATE(Parametros!$B$20,10,1),Proyectos!$D$5:$D$204,"<"&DATE(Parametros!$B$20,10+1,1)) | F14: =SUMIFS(Gastos!$D$5:$D$204,Gastos!$A$5:$A$204,">="&DATE(Parametros!$B$20,10,1),Gastos!$A$5:$A$204,"<"&DATE(Parametros!$B$20,10+1,1)) | G14: =E14-F14 | H14: =G14*Parametros!$C$5 | I14: =G14*Parametros!$C$6
A15: Noviembre | B15: =SUMIFS(Proyectos!$J$5:$J$204,Proyectos!$D$5:$D$204,">="&DATE(Parametros!$B$20,11,1),Proyectos!$D$5:$D$204,"<"&DATE(Parametros!$B$20,11+1,1)) | C15: =SUMIFS(Proyectos!$U$5:$U$204,Proyectos!$D$5:$D$204,">="&DATE(Parametros!$B$20,11,1),Proyectos!$D$5:$D$204,"<"&DATE(Parametros!$B$20,11+1,1)) | D15: =SUMIFS(Proyectos!$V$5:$V$204,Proyectos!$D$5:$D$204,">="&DATE(Parametros!$B$20,11,1),Proyectos!$D$5:$D$204,"<"&DATE(Parametros!$B$20,11+1,1)) | E15: =SUMIFS(Proyectos!$N$5:$N$204,Proyectos!$D$5:$D$204,">="&DATE(Parametros!$B$20,11,1),Proyectos!$D$5:$D$204,"<"&DATE(Parametros!$B$20,11+1,1)) | F15: =SUMIFS(Gastos!$D$5:$D$204,Gastos!$A$5:$A$204,">="&DATE(Parametros!$B$20,11,1),Gastos!$A$5:$A$204,"<"&DATE(Parametros!$B$20,11+1,1)) | G15: =E15-F15 | H15: =G15*Parametros!$C$5 | I15: =G15*Parametros!$C$6
A16: Diciembre | B16: =SUMIFS(Proyectos!$J$5:$J$204,Proyectos!$D$5:$D$204,">="&DATE(Parametros!$B$20,12,1),Proyectos!$D$5:$D$204,"<"&DATE(Parametros!$B$20,12+1,1)) | C16: =SUMIFS(Proyectos!$U$5:$U$204,Proyectos!$D$5:$D$204,">="&DATE(Parametros!$B$20,12,1),Proyectos!$D$5:$D$204,"<"&DATE(Parametros!$B$20,12+1,1)) | D16: =SUMIFS(Proyectos!$V$5:$V$204,Proyectos!$D$5:$D$204,">="&DATE(Parametros!$B$20,12,1),Proyectos!$D$5:$D$204,"<"&DATE(Parametros!$B$20,12+1,1)) | E16: =SUMIFS(Proyectos!$N$5:$N$204,Proyectos!$D$5:$D$204,">="&DATE(Parametros!$B$20,12,1),Proyectos!$D$5:$D$204,"<"&DATE(Parametros!$B$20,12+1,1)) | F16: =SUMIFS(Gastos!$D$5:$D$204,Gastos!$A$5:$A$204,">="&DATE(Parametros!$B$20,12,1),Gastos!$A$5:$A$204,"<"&DATE(Parametros!$B$20,12+1,1)) | G16: =E16-F16 | H16: =G16*Parametros!$C$5 | I16: =G16*Parametros!$C$6
A17: TOTAL AÑO | B17: =SUM(B5:B16) | C17: =SUM(C5:C16) | D17: =SUM(D5:D16) | E17: =SUM(E5:E16) | F17: =SUM(F5:F16) | G17: =SUM(G5:G16) | H17: =SUM(H5:H16) | I17: =SUM(I5:I16)
A18: Control: ingreso neto = trabajo + fondo | B18: =IF(ROUND(B17-C17-D17-E17,2)=0,"OK","Revisar")
A20: Cierre del año: utilidad de la empresa y dividendos (aproximación)
A21: Fondo Bouw acumulado del año | B21: =E17
A22: (−) Gastos de la empresa | B22: =-F17
A23: Utilidad antes de participación e impuestos | B23: =B21+B22
A24: (−) Participación de trabajadores | B24: =IF(AND(Parametros!B21="Sí",B23>0),-B23*Parametros!B22,0)
A25: Base del impuesto a la renta | B25: =B23+B24
A26: (−) Impuesto a la renta de la sociedad | B26: =IF(B25>0,-B25*Parametros!B23,0)
A27: Utilidad neta | B27: =B25+B26
A28: (−) Reserva | B28: =IF(B27>0,-B27*Parametros!B24,0)
A29: (−) Reinversión acordada | B29: =IF(B27>0,-(B27+B28)*Parametros!B25,0)
A30: Dividendos a repartir | B30: =MAX(0,B27+B28+B29)
A33: Por socio (año)
A34: Concepto | B34: =Parametros!B5 | C34: =Parametros!B6
A35: Pago por trabajo (origen + líder + ejecución) | B35: =C17 | C35: =D17
A36: Dividendo bruto (según propiedad) | B36: =$B$30*Parametros!C5 | C36: =$B$30*Parametros!C6
A37: Retención sobre dividendos | B37: =-MAX(0,B36-Parametros!$B$29)*Parametros!$B$26 | C37: =-MAX(0,C36-Parametros!$B$29)*Parametros!$B$26
A38: Dividendo neto | B38: =B36+B37 | C38: =C36+C37
A39: TOTAL que recibe en el año (antes de impuestos personales sobre honorarios) | B39: =B35+B38 | C39: =C35+C38
A40: % del total recibido por los dos | B40: =IF(($B$39+$C$39)=0,0,B39/($B$39+$C$39)) | C40: =IF(($B$39+$C$39)=0,0,C39/($B$39+$C$39))
A42: Lectura: la fila 35 premia a quien consigue, lidera y trabaja más. Las filas 36–38 son iguales para los dos porque ambos son dueños.
A43: La retención se aplica sobre lo que excede la franja exenta por socio (Parametros B29). Validar con el contador.

Sheet Horas
A1: Registro de horas
A2: Una fila por bloque de trabajo. El ID de proyecto debe ser igual al de la hoja Proyectos.
A4: Fecha | B4: ID proyecto | C4: Socio | D4: Horas | E4: Tarea | F4: Nota
A5: 46301 | B5: P-001 | C5: =Parametros!$B$5 | D5: 12 | E5: Diagnóstico y mapeo de procesos | F5: EJEMPLO
A6: 46303 | B6: P-001 | C6: =Parametros!$B$6 | D6: 8 | E6: Revisión de seguridad y respaldos | F6: EJEMPLO
A7: 46310 | B7: P-001 | C7: =Parametros!$B$5 | D7: 18 | E7: Rediseño y automatización | F7: EJEMPLO
A8: 46315 | B8: P-001 | C8: =Parametros!$B$6 | D8: 12 | E8: Configuración de accesos | F8: EJEMPLO
A9: 46330 | B9: P-002 | C9: =Parametros!$B$6 | D9: 21 | E9: Plan de seguridad y continuidad | F9: EJEMPLO
A10: 46336 | B10: P-002 | C10: =Parametros!$B$5 | D10: 9 | E10: Procesos de respaldo operativo | F10: EJEMPLO
F11: Nota: en las filas de ejemplo el socio viene de Parametros (verde). En sus filas elijan el nombre del desplegable.

Sheet Proyectos
A1: Proyectos y reparto por trabajo
A2: Una fila por proyecto (o por cada mes de un cliente recurrente). Llenen solo las columnas A–I (azules). El resto se calcula.
A4: ID proyecto | B4: Cliente | C4: Tipo | D4: Fecha de cobro | E4: Ingreso cobrado sin IVA (USD) | F4: Costos directos (USD) | G4: Quién consiguió el cliente | H4: Líder del proyecto | I4: Nota | J4: Ingreso neto (USD) | K4: Horas socio 1 | L4: Horas socio 2 | M4: % ejecución socio 1 | N4: Fondo Bouw (USD) | O4: Origen socio 1 | P4: Origen socio 2 | Q4: Líder socio 1 | R4: Líder socio 2 | S4: Ejecución socio 1 | T4: Ejecución socio 2 | U4: TOTAL trabajo socio 1 (USD) | V4: TOTAL trabajo socio 2 (USD) | W4: Control (debe ser 0)
A5: P-001 | B5: Distribuidora (ejemplo) | C5: Procesos | D5: 46326 | E5: 4000 | F5: 400 | G5: =Parametros!$B$5 | H5: =Parametros!$B$5 | I5: EJEMPLO | J5: =IF($E5="","",E5-F5) | K5: =IF($A5="","",SUMIFS(Horas!$D:$D,Horas!$B:$B,$A5,Horas!$C:$C,Parametros!$B$5)) | L5: =IF($A5="","",SUMIFS(Horas!$D:$D,Horas!$B:$B,$A5,Horas!$C:$C,Parametros!$B$6)) | M5: =IF($E5="","",IF(N(K5)+N(L5)=0,Parametros!$C$5,N(K5)/(N(K5)+N(L5)))) | N5: =IF($E5="","",J5*Parametros!$B$11+IF(G5=Parametros!$B$16,J5*Parametros!$B$12,0)) | O5: =IF($E5="","",IF(G5=Parametros!$B$5,J5*Parametros!$B$12,0)) | P5: =IF($E5="","",IF(G5=Parametros!$B$6,J5*Parametros!$B$12,0)) | Q5: =IF($E5="","",IF(H5=Parametros!$B$5,J5*Parametros!$B$13,IF(H5=Parametros!$B$6,0,J5*Parametros!$B$13*Parametros!$C$5))) | R5: =IF($E5="","",IF(H5=Parametros!$B$6,J5*Parametros!$B$13,IF(H5=Parametros!$B$5,0,J5*Parametros!$B$13*Parametros!$C$6))) | S5: =IF($E5="","",J5*Parametros!$B$14*M5) | T5: =IF($E5="","",J5*Parametros!$B$14*(1-M5)) | U5: =IF($E5="","",O5+Q5+S5) | V5: =IF($E5="","",P5+R5+T5) | W5: =IF($E5="","",ROUND(J5-N5-U5-V5,2))
A6: P-002 | B6: Clínica (ejemplo) | C6: Seguridad | D6: 46356 | E6: 4000 | F6: 400 | G6: =Parametros!$B$6 | H6: =Parametros!$B$6 | I6: EJEMPLO | J6: =IF($E6="","",E6-F6) | K6: =IF($A6="","",SUMIFS(Horas!$D:$D,Horas!$B:$B,$A6,Horas!$C:$C,Parametros!$B$5)) | L6: =IF($A6="","",SUMIFS(Horas!$D:$D,Horas!$B:$B,$A6,Horas!$C:$C,Parametros!$B$6)) | M6: =IF($E6="","",IF(N(K6)+N(L6)=0,Parametros!$C$5,N(K6)/(N(K6)+N(L6)))) | N6: =IF($E6="","",J6*Parametros!$B$11+IF(G6=Parametros!$B$16,J6*Parametros!$B$12,0)) | O6: =IF($E6="","",IF(G6=Parametros!$B$5,J6*Parametros!$B$12,0)) | P6: =IF($E6="","",IF(G6=Parametros!$B$6,J6*Parametros!$B$12,0)) | Q6: =IF($E6="","",IF(H6=Parametros!$B$5,J6*Parametros!$B$13,IF(H6=Parametros!$B$6,0,J6*Parametros!$B$13*Parametros!$C$5))) | R6: =IF($E6="","",IF(H6=Parametros!$B$6,J6*Parametros!$B$13,IF(H6=Parametros!$B$5,0,J6*Parametros!$B$13*Parametros!$C$6))) | S6: =IF($E6="","",J6*Parametros!$B$14*M6) | T6: =IF($E6="","",J6*Parametros!$B$14*(1-M6)) | U6: =IF($E6="","",O6+Q6+S6) | V6: =IF($E6="","",P6+R6+T6) | W6: =IF($E6="","",ROUND(J6-N6-U6-V6,2))
J7: =IF($E7="","",E7-F7) | K7: =IF($A7="","",SUMIFS(Horas!$D:$D,Horas!$B:$B,$A7,Horas!$C:$C,Parametros!$B$5)) | L7: =IF($A7="","",SUMIFS(Horas!$D:$D,Horas!$B:$B,$A7,Horas!$C:$C,Parametros!$B$6)) | M7: =IF($E7="","",IF(N(K7)+N(L7)=0,Parametros!$C$5,N(K7)/(N(K7)+N(L7)))) | N7: =IF($E7="","",J7*Parametros!$B$11+IF(G7=Parametros!$B$16,J7*Parametros!$B$12,0)) | O7: =IF($E7="","",IF(G7=Parametros!$B$5,J7*Parametros!$B$12,0)) | P7: =IF($E7="","",IF(G7=Parametros!$B$6,J7*Parametros!$B$12,0)) | Q7: =IF($E7="","",IF(H7=Parametros!$B$5,J7*Parametros!$B$13,IF(H7=Parametros!$B$6,0,J7*Parametros!$B$13*Parametros!$C$5))) | R7: =IF($E7="","",IF(H7=Parametros!$B$6,J7*Parametros!$B$13,IF(H7=Parametros!$B$5,0,J7*Parametros!$B$13*Parametros!$C$6))) | S7: =IF($E7="","",J7*Parametros!$B$14*M7) | T7: =IF($E7="","",J7*Parametros!$B$14*(1-M7)) | U7: =IF($E7="","",O7+Q7+S7) | V7: =IF($E7="","",P7+R7+T7) | W7: =IF($E7="","",ROUND(J7-N7-U7-V7,2))
J8: =IF($E8="","",E8-F8) | K8: =IF($A8="","",SUMIFS(Horas!$D:$D,Horas!$B:$B,$A8,Horas!$C:$C,Parametros!$B$5)) | L8: =IF($A8="","",SUMIFS(Horas!$D:$D,Horas!$B:$B,$A8,Horas!$C:$C,Parametros!$B$6)) | M8: =IF($E8="","",IF(N(K8)+N(L8)=0,Parametros!$C$5,N(K8)/(N(K8)+N(L8)))) | N8: =IF($E8="","",J8*Parametros!$B$11+IF(G8=Parametros!$B$16,J8*Parametros!$B$12,0)) | O8: =IF($E8="","",IF(G8=Parametros!$B$5,J8*Parametros!$B$12,0)) | P8: =IF($E8="","",IF(G8=Parametros!$B$6,J8*Parametros!$B$12,0)) | Q8: =IF($E8="","",IF(H8=Parametros!$B$5,J8*Parametros!$B$13,IF(H8=Parametros!$B$6,0,J8*Parametros!$B$13*Parametros!$C$5))) | R8: =IF($E8="","",IF(H8=Parametros!$B$6,J8*Parametros!$B$13,IF(H8=Parametros!$B$5,0,J8*Parametros!$B$13*Parametros!$C$6))) | S8: =IF($E8="","",J8*Parametros!$B$14*M8) | T8: =IF($E8="","",J8*Parametros!$B$14*(1-M8)) | U8: =IF($E8="","",O8+Q8+S8) | V8: =IF($E8="","",P8+R8+T8) | W8: =IF($E8="","",ROUND(J8-N8-U8-V8,2))
J9: =IF($E9="","",E9-F9) | K9: =IF($A9="","",SUMIFS(Horas!$D:$D,Horas!$B:$B,$A9,Horas!$C:$C,Parametros!$B$5)) | L9: =IF($A9="","",SUMIFS(Horas!$D:$D,Horas!$B:$B,$A9,Horas!$C:$C,Parametros!$B$6)) | M9: =IF($E9="","",IF(N(K9)+N(L9)=0,Parametros!$C$5,N(K9)/(N(K9)+N(L9)))) | N9: =IF($E9="","",J9*Parametros!$B$11+IF(G9=Parametros!$B$16,J9*Parametros!$B$12,0)) | O9: =IF($E9="","",IF(G9=Parametros!$B$5,J9*Parametros!$B$12,0)) | P9: =IF($E9="","",IF(G9=Parametros!$B$6,J9*Parametros!$B$12,0)) | Q9: =IF($E9="","",IF(H9=Parametros!$B$5,J9*Parametros!$B$13,IF(H9=Parametros!$B$6,0,J9*Parametros!$B$13*Parametros!$C$5))) | R9: =IF($E9="","",IF(H9=Parametros!$B$6,J9*Parametros!$B$13,IF(H9=Parametros!$B$5,0,J9*Parametros!$B$13*Parametros!$C$6))) | S9: =IF($E9="","",J9*Parametros!$B$14*M9) | T9: =IF($E9="","",J9*Parametros!$B$14*(1-M9)) | U9: =IF($E9="","",O9+Q9+S9) | V9: =IF($E9="","",P9+R9+T9) | W9: =IF($E9="","",ROUND(J9-N9-U9-V9,2))
J10: =IF($E10="","",E10-F10) | K10: =IF($A10="","",SUMIFS(Horas!$D:$D,Horas!$B:$B,$A10,Horas!$C:$C,Parametros!$B$5)) | L10: =IF($A10="","",SUMIFS(Horas!$D:$D,Horas!$B:$B,$A10,Horas!$C:$C,Parametros!$B$6)) | M10: =IF($E10="","",IF(N(K10)+N(L10)=0,Parametros!$C$5,N(K10)/(N(K10)+N(L10)))) | N10: =IF($E10="","",J10*Parametros!$B$11+IF(G10=Parametros!$B$16,J10*Parametros!$B$12,0)) | O10: =IF($E10="","",IF(G10=Parametros!$B$5,J10*Parametros!$B$12,0)) | P10: =IF($E10="","",IF(G10=Parametros!$B$6,J10*Parametros!$B$12,0)) | Q10: =IF($E10="","",IF(H10=Parametros!$B$5,J10*Parametros!$B$13,IF(H10=Parametros!$B$6,0,J10*Parametros!$B$13*Parametros!$C$5))) | R10: =IF($E10="","",IF(H10=Parametros!$B$6,J10*Parametros!$B$13,IF(H10=Parametros!$B$5,0,J10*Parametros!$B$13*Parametros!$C$6))) | S10: =IF($E10="","",J10*Parametros!$B$14*M10) | T10: =IF($E10="","",J10*Parametros!$B$14*(1-M10)) | U10: =IF($E10="","",O10+Q10+S10) | V10: =IF($E10="","",P10+R10+T10) | W10: =IF($E10="","",ROUND(J10-N10-U10-V10,2))
J11: =IF($E11="","",E11-F11) | K11: =IF($A11="","",SUMIFS(Horas!$D:$D,Horas!$B:$B,$A11,Horas!$C:$C,Parametros!$B$5)) | L11: =IF($A11="","",SUMIFS(Horas!$D:$D,Horas!$B:$B,$A11,Horas!$C:$C,Parametros!$B$6)) | M11: =IF($E11="","",IF(N(K11)+N(L11)=0,Parametros!$C$5,N(K11)/(N(K11)+N(L11)))) | N11: =IF($E11="","",J11*Parametros!$B$11+IF(G11=Parametros!$B$16,J11*Parametros!$B$12,0)) | O11: =IF($E11="","",IF(G11=Parametros!$B$5,J11*Parametros!$B$12,0)) | P11: =IF($E11="","",IF(G11=Parametros!$B$6,J11*Parametros!$B$12,0)) | Q11: =IF($E11="","",IF(H11=Parametros!$B$5,J11*Parametros!$B$13,IF(H11=Parametros!$B$6,0,J11*Parametros!$B$13*Parametros!$C$5))) | R11: =IF($E11="","",IF(H11=Parametros!$B$6,J11*Parametros!$B$13,IF(H11=Parametros!$B$5,0,J11*Parametros!$B$13*Parametros!$C$6))) | S11: =IF($E11="","",J11*Parametros!$B$14*M11) | T11: =IF($E11="","",J11*Parametros!$B$14*(1-M11)) | U11: =IF($E11="","",O11+Q11+S11) | V11: =IF($E11="","",P11+R11+T11) | W11: =IF($E11="","",ROUND(J11-N11-U11-V11,2))
J12: =IF($E12="","",E12-F12) | K12: =IF($A12="","",SUMIFS(Horas!$D:$D,Horas!$B:$B,$A12,Horas!$C:$C,Parametros!$B$5)) | L12: =IF($A12="","",SUMIFS(Horas!$D:$D,Horas!$B:$B,$A12,Horas!$C:$C,Parametros!$B$6)) | M12: =IF($E12="","",IF(N(K12)+N(L12)=0,Parametros!$C$5,N(K12)/(N(K12)+N(L12)))) | N12: =IF($E12="","",J12*Parametros!$B$11+IF(G12=Parametros!$B$16,J12*Parametros!$B$12,0)) | O12: =IF($E12="","",IF(G12=Parametros!$B$5,J12*Parametros!$B$12,0)) | P12: =IF($E12="","",IF(G12=Parametros!$B$6,J12*Parametros!$B$12,0)) | Q12: =IF($E12="","",IF(H12=Parametros!$B$5,J12*Parametros!$B$13,IF(H12=Parametros!$B$6,0,J12*Parametros!$B$13*Parametros!$C$5))) | R12: =IF($E12="","",IF(H12=Parametros!$B$6,J12*Parametros!$B$13,IF(H12=Parametros!$B$5,0,J12*Parametros!$B$13*Parametros!$C$6))) | S12: =IF($E12="","",J12*Parametros!$B$14*M12) | T12: =IF($E12="","",J12*Parametros!$B$14*(1-M12)) | U12: =IF($E12="","",O12+Q12+S12) | V12: =IF($E12="","",P12+R12+T12) | W12: =IF($E12="","",ROUND(J12-N12-U12-V12,2))
J13: =IF($E13="","",E13-F13) | K13: =IF($A13="","",SUMIFS(Horas!$D:$D,Horas!$B:$B,$A13,Horas!$C:$C,Parametros!$B$5)) | L13: =IF($A13="","",SUMIFS(Horas!$D:$D,Horas!$B:$B,$A13,Horas!$C:$C,Parametros!$B$6)) | M13: =IF($E13="","",IF(N(K13)+N(L13)=0,Parametros!$C$5,N(K13)/(N(K13)+N(L13)))) | N13: =IF($E13="","",J13*Parametros!$B$11+IF(G13=Parametros!$B$16,J13*Parametros!$B$12,0)) | O13: =IF($E13="","",IF(G13=Parametros!$B$5,J13*Parametros!$B$12,0)) | P13: =IF($E13="","",IF(G13=Parametros!$B$6,J13*Parametros!$B$12,0)) | Q13: =IF($E13="","",IF(H13=Parametros!$B$5,J13*Parametros!$B$13,IF(H13=Parametros!$B$6,0,J13*Parametros!$B$13*Parametros!$C$5))) | R13: =IF($E13="","",IF(H13=Parametros!$B$6,J13*Parametros!$B$13,IF(H13=Parametros!$B$5,0,J13*Parametros!$B$13*Parametros!$C$6))) | S13: =IF($E13="","",J13*Parametros!$B$14*M13) | T13: =IF($E13="","",J13*Parametros!$B$14*(1-M13)) | U13: =IF($E13="","",O13+Q13+S13) | V13: =IF($E13="","",P13+R13+T13) | W13: =IF($E13="","",ROUND(J13-N13-U13-V13,2))
J14: =IF($E14="","",E14-F14) | K14: =IF($A14="","",SUMIFS(Horas!$D:$D,Horas!$B:$B,$A14,Horas!$C:$C,Parametros!$B$5)) | L14: =IF($A14="","",SUMIFS(Horas!$D:$D,Horas!$B:$B,$A14,Horas!$C:$C,Parametros!$B$6)) | M14: =IF($E14="","",IF(N(K14)+N(L14)=0,Parametros!$C$5,N(K14)/(N(K14)+N(L14)))) | N14: =IF($E14="","",J14*Parametros!$B$11+IF(G14=Parametros!$B$16,J14*Parametros!$B$12,0)) | O14: =IF($E14="","",IF(G14=Parametros!$B$5,J14*Parametros!$B$12,0)) | P14: =IF($E14="","",IF(G14=Parametros!$B$6,J14*Parametros!$B$12,0)) | Q14: =IF($E14="","",IF(H14=Parametros!$B$5,J14*Parametros!$B$13,IF(H14=Parametros!$B$6,0,J14*Parametros!$B$13*Parametros!$C$5))) | R14: =IF($E14="","",IF(H14=Parametros!$B$6,J14*Parametros!$B$13,IF(H14=Parametros!$B$5,0,J14*Parametros!$B$13*Parametros!$C$6))) | S14: =IF($E14="","",J14*Parametros!$B$14*M14) | T14: =IF($E14="","",J14*Parametros!$B$14*(1-M14)) | U14: =IF($E14="","",O14+Q14+S14) | V14: =IF($E14="","",P14+R14+T14) | W14: =IF($E14="","",ROUND(J14-N14-U14-V14,2))
J15: =IF($E15="","",E15-F15) | K15: =IF($A15="","",SUMIFS(Horas!$D:$D,Horas!$B:$B,$A15,Horas!$C:$C,Parametros!$B$5)) | L15: =IF($A15="","",SUMIFS(Horas!$D:$D,Horas!$B:$B,$A15,Horas!$C:$C,Parametros!$B$6)) | M15: =IF($E15="","",IF(N(K15)+N(L15)=0,Parametros!$C$5,N(K15)/(N(K15)+N(L15)))) | N15: =IF($E15="","",J15*Parametros!$B$11+IF(G15=Parametros!$B$16,J15*Parametros!$B$12,0)) | O15: =IF($E15="","",IF(G15=Parametros!$B$5,J15*Parametros!$B$12,0)) | P15: =IF($E15="","",IF(G15=Parametros!$B$6,J15*Parametros!$B$12,0)) | Q15: =IF($E15="","",IF(H15=Parametros!$B$5,J15*Parametros!$B$13,IF(H15=Parametros!$B$6,0,J15*Parametros!$B$13*Parametros!$C$5))) | R15: =IF($E15="","",IF(H15=Parametros!$B$6,J15*Parametros!$B$13,IF(H15=Parametros!$B$5,0,J15*Parametros!$B$13*Parametros!$C$6))) | S15: =IF($E15="","",J15*Parametros!$B$14*M15) | T15: =IF($E15="","",J15*Parametros!$B$14*(1-M15)) | U15: =IF($E15="","",O15+Q15+S15) | V15: =IF($E15="","",P15+R15+T15) | W15: =IF($E15="","",ROUND(J15-N15-U15-V15,2))
J16: =IF($E16="","",E16-F16) | K16: =IF($A16="","",SUMIFS(Horas!$D:$D,Horas!$B:$B,$A16,Horas!$C:$C,Parametros!$B$5)) | L16: =IF($A16="","",SUMIFS(Horas!$D:$D,Horas!$B:$B,$A16,Horas!$C:$C,Parametros!$B$6)) | M16: =IF($E16="","",IF(N(K16)+N(L16)=0,Parametros!$C$5,N(K16)/(N(K16)+N(L16)))) | N16: =IF($E16="","",J16*Parametros!$B$11+IF(G16=Parametros!$B$16,J16*Parametros!$B$12,0)) | O16: =IF($E16="","",IF(G16=Parametros!$B$5,J16*Parametros!$B$12,0)) | P16: =IF($E16="","",IF(G16=Parametros!$B$6,J16*Parametros!$B$12,0)) | Q16: =IF($E16="","",IF(H16=Parametros!$B$5,J16*Parametros!$B$13,IF(H16=Parametros!$B$6,0,J16*Parametros!$B$13*Parametros!$C$5))) | R16: =IF($E16="","",IF(H16=Parametros!$B$6,J16*Parametros!$B$13,IF(H16=Parametros!$B$5,0,J16*Parametros!$B$13*Parametros!$C$6))) | S16: =IF($E16="","",J16*Parametros!$B$14*M16) | T16: =IF($E16="","",J16*Parametros!$B$14*(1-M16)) | U16: =IF($E16="","",O16+Q16+S16) | V16: =IF($E16="","",P16+R16+T16) | W16: =IF($E16="","",ROUND(J16-N16-U16-V16,2))
J17: =IF($E17="","",E17-F17) | K17: =IF($A17="","",SUMIFS(Horas!$D:$D,Horas!$B:$B,$A17,Horas!$C:$C,Parametros!$B$5)) | L17: =IF($A17="","",SUMIFS(Horas!$D:$D,Horas!$B:$B,$A17,Horas!$C:$C,Parametros!$B$6)) | M17: =IF($E17="","",IF(N(K17)+N(L17)=0,Parametros!$C$5,N(K17)/(N(K17)+N(L17)))) | N17: =IF($E17="","",J17*Parametros!$B$11+IF(G17=Parametros!$B$16,J17*Parametros!$B$12,0)) | O17: =IF($E17="","",IF(G17=Parametros!$B$5,J17*Parametros!$B$12,0)) | P17: =IF($E17="","",IF(G17=Parametros!$B$6,J17*Parametros!$B$12,0)) | Q17: =IF($E17="","",IF(H17=Parametros!$B$5,J17*Parametros!$B$13,IF(H17=Parametros!$B$6,0,J17*Parametros!$B$13*Parametros!$C$5))) | R17: =IF($E17="","",IF(H17=Parametros!$B$6,J17*Parametros!$B$13,IF(H17=Parametros!$B$5,0,J17*Parametros!$B$13*Parametros!$C$6))) | S17: =IF($E17="","",J17*Parametros!$B$14*M17) | T17: =IF($E17="","",J17*Parametros!$B$14*(1-M17)) | U17: =IF($E17="","",O17+Q17+S17) | V17: =IF($E17="","",P17+R17+T17) | W17: =IF($E17="","",ROUND(J17-N17-U17-V17,2))
J18: =IF($E18="","",E18-F18) | K18: =IF($A18="","",SUMIFS(Horas!$D:$D,Horas!$B:$B,$A18,Horas!$C:$C,Parametros!$B$5)) | L18: =IF($A18="","",SUMIFS(Horas!$D:$D,Horas!$B:$B,$A18,Horas!$C:$C,Parametros!$B$6)) | M18: =IF($E18="","",IF(N(K18)+N(L18)=0,Parametros!$C$5,N(K18)/(N(K18)+N(L18)))) | N18: =IF($E18="","",J18*Parametros!$B$11+IF(G18=Parametros!$B$16,J18*Parametros!$B$12,0)) | O18: =IF($E18="","",IF(G18=Parametros!$B$5,J18*Parametros!$B$12,0)) | P18: =IF($E18="","",IF(G18=Parametros!$B$6,J18*Parametros!$B$12,0)) | Q18: =IF($E18="","",IF(H18=Parametros!$B$5,J18*Parametros!$B$13,IF(H18=Parametros!$B$6,0,J18*Parametros!$B$13*Parametros!$C$5))) | R18: =IF($E18="","",IF(H18=Parametros!$B$6,J18*Parametros!$B$13,IF(H18=Parametros!$B$5,0,J18*Parametros!$B$13*Parametros!$C$6))) | S18: =IF($E18="","",J18*Parametros!$B$14*M18) | T18: =IF($E18="","",J18*Parametros!$B$14*(1-M18)) | U18: =IF($E18="","",O18+Q18+S18) | V18: =IF($E18="","",P18+R18+T18) | W18: =IF($E18="","",ROUND(J18-N18-U18-V18,2))
... J204: =IF($E204="","",E204-F204) | K204: =IF($A204="","",SUMIFS(Horas!$D:$D,Horas!$B:$B,$A204,Horas!$C:$C,Parametros!$B$5)) | L204: =IF($A204="","",SUMIFS(Horas!$D:$D,Horas!$B:$B,$A204,Horas!$C:$C,Parametros!$B$6)) | M204: =IF($E204="","",IF(N(K204)+N(L204)=0,Parametros!$C$5,N(K204)/(N(K204)+N(L204)))) | N204: =IF($E204="","",J204*Parametros!$B$11+IF(G204=Parametros!$B$16,J204*Parametros!$B$12,0)) | O204: =IF($E204="","",IF(G204=Parametros!$B$5,J204*Parametros!$B$12,0)) | P204: =IF($E204="","",IF(G204=Parametros!$B$6,J204*Parametros!$B$12,0)) | Q204: =IF($E204="","",IF(H204=Parametros!$B$5,J204*Parametros!$B$13,IF(H204=Parametros!$B$6,0,J204*Parametros!$B$13*Parametros!$C$5))) | R204: =IF($E204="","",IF(H204=Parametros!$B$6,J204*Parametros!$B$13,IF(H204=Parametros!$B$5,0,J204*Parametros!$B$13*Parametros!$C$6))) | S204: =IF($E204="","",J204*Parametros!$B$14*M204) | T204: =IF($E204="","",J204*Parametros!$B$14*(1-M204)) | U204: =IF($E204="","",O204+Q204+S204) | V204: =IF($E204="","",P204+R204+T204) | W204: =IF($E204="","",ROUND(J204-N204-U204-V204,2))
A205: TOTALES | E205: =SUM(E5:E204) | F205: =SUM(F5:F204) | J205: =SUM(J5:J204) | K205: =SUM(K5:K204) | L205: =SUM(L5:L204) | N205: =SUM(N5:N204) | O205: =SUM(O5:O204) | P205: =SUM(P5:P204) | Q205: =SUM(Q5:Q204) | R205: =SUM(R5:R204) | S205: =SUM(S5:S204) | T205: =SUM(T5:T204) | U205: =SUM(U5:U204) | ... W205: =SUM(W5:W204)

Sheet Gastos
A1: Gastos de la empresa (pagados con el Fondo Bouw)
A4: Fecha | B4: Concepto | C4: Categoría | D4: Monto sin IVA (USD) | E4: Nota
A5: 46296 | B5: Contador mensual | C5: Contabilidad | D5: 80 | E5: EJEMPLO
A6: 46300 | B6: Dominio y hosting de la web | C6: Herramientas | D6: 20 | E6: EJEMPLO
A7: 46305 | B7: Publicidad en Facebook | C7: Marketing | D7: 100 | E7: EJEMPLO
A205: TOTAL | D205: =SUM(D5:D204)
